README.md
setup.cfg
setup.py
affirm/__init__.py
affirm/client.py
affirm/errors.py
affirm/constants/__init__.py
affirm/constants/error_code.py
affirm/constants/http_status_code.py
affirm/constants/url.py
affirm/resources/__init__.py
affirm/resources/base.py
affirm/resources/charge.py
affirm_pay.egg-info/PKG-INFO
affirm_pay.egg-info/SOURCES.txt
affirm_pay.egg-info/dependency_links.txt
affirm_pay.egg-info/requires.txt
affirm_pay.egg-info/top_level.txt